ScreenShotPlayer.py
resource/__init__.py
resource/controller.js
resource/data.js
resource/style.css
robot_screenshot_player-0.0.8.dist-info/LICENSE
robot_screenshot_player-0.0.8.dist-info/METADATA
robot_screenshot_player-0.0.8.dist-info/WHEEL
robot_screenshot_player-0.0.8.dist-info/top_level.txt
robot_screenshot_player-0.0.8.dist-info/RECORD
